ormrepo/__init__.py
ormrepo/db_settings.py
ormrepo/exceptions.py
ormrepo/logger.py
ormrepo/mapper.py
ormrepo/models.py
ormrepo/orm.py
ormrepo/types_.py
ormrepo/utils.py
ormrepo-0.5.0.dist-info/METADATA
ormrepo-0.5.0.dist-info/WHEEL
ormrepo-0.5.0.dist-info/RECORD
